http_relay/__init__.py
http_relay/__main__.py
http_relay/relay.py
http_relay-2.1.3.dist-info/LICENSE
http_relay-2.1.3.dist-info/METADATA
http_relay-2.1.3.dist-info/WHEEL
http_relay-2.1.3.dist-info/entry_points.txt
http_relay-2.1.3.dist-info/top_level.txt
http_relay-2.1.3.dist-info/RECORD
