Metadata-Version: 2.1
Name: http-relay
Version: 2.1.3
Summary: Relay for HTTP messages (reverse proxy)
Home-page: https://github.com/ctu-vras/http_relay
Author: Martin Pecka
Author-email: Martin Pecka <peci1@seznam.cz>
Maintainer: Martin Pecka
Maintainer-email: Martin Pecka <peci1@seznam.cz>
License: BSD 3-Clause License
Project-URL: Homepage, https://github.com/ctu-vras/http_relay
Keywords: http,proxy
Classifier: License :: OSI Approved :: BSD License
Classifier: Programming Language :: Python
Classifier: Programming Language :: Python :: 2
Classifier: Programming Language :: Python :: 3
Classifier: Development Status :: 5 - Production/Stable
Classifier: Environment :: Console
Classifier: Intended Audience :: Developers
Classifier: Intended Audience :: Information Technology
Classifier: Intended Audience :: Science/Research
Classifier: Operating System :: OS Independent
Classifier: Topic :: Communications
Classifier: Topic :: Internet
Classifier: Topic :: Internet :: WWW/HTTP
Classifier: Topic :: Internet :: WWW/HTTP :: HTTP Servers
Classifier: Topic :: Software Development :: Libraries
Classifier: Topic :: System :: Networking
Classifier: Topic :: Utilities
Requires-Python: >=2.7
License-File: LICENSE
Provides-Extra: test
Requires-Dist: pytest ; extra == 'test'
